ffmpeg_converter/__init__.py
ffmpeg_converter/audio.py
ffmpeg_converter/base.py
ffmpeg_converter/py.typed
ffmpeg_converter/video.py
ffmpeg_converter-0.3.7.dist-info/licenses/LICENSE
ffmpeg_converter-0.3.7.dist-info/METADATA
ffmpeg_converter-0.3.7.dist-info/WHEEL
ffmpeg_converter-0.3.7.dist-info/top_level.txt
ffmpeg_converter-0.3.7.dist-info/RECORD
