Metadata-Version: 2.4
Name: ffmpeg-converter
Version: 0.3.7
Summary: 基于 FFmpeg 的音视频格式转换工具
Author-email: OSpoon <zxin088@gmail.com>
License: MIT License
Project-URL: Homepage, https://github.com/OSpoon/ffmpeg-converter/
Project-URL: Bug Tracker, https://github.com/OSpoon/ffmpeg-converter/issues
Keywords: ffmpeg,converter,audio,video
Classifier: Programming Language :: Python :: 3
Classifier: License :: OSI Approved :: MIT License
Classifier: Operating System :: OS Independent
Requires-Python: >=3.11
License-File: LICENSE
Dynamic: license-file
